odoo/addons/sale_order_type_quotation_number/README.rst
odoo/addons/sale_order_type_quotation_number/__init__.py
odoo/addons/sale_order_type_quotation_number/__manifest__.py
odoo/addons/sale_order_type_quotation_number/i18n/es.po
odoo/addons/sale_order_type_quotation_number/i18n/sale_order_type_quotation_number.pot
odoo/addons/sale_order_type_quotation_number/models/__init__.py
odoo/addons/sale_order_type_quotation_number/models/sale_order.py
odoo/addons/sale_order_type_quotation_number/models/sale_order_type.py
odoo/addons/sale_order_type_quotation_number/readme/CONFIGURE.rst
odoo/addons/sale_order_type_quotation_number/readme/CONTRIBUTORS.rst
odoo/addons/sale_order_type_quotation_number/readme/DESCRIPTION.rst
odoo/addons/sale_order_type_quotation_number/readme/ROADMAP.rst
odoo/addons/sale_order_type_quotation_number/readme/USAGE.rst
odoo/addons/sale_order_type_quotation_number/static/description/icon.png
odoo/addons/sale_order_type_quotation_number/static/description/index.html
odoo/addons/sale_order_type_quotation_number/tests/__init__.py
odoo/addons/sale_order_type_quotation_number/tests/test_sale_order_type_quotation_number.py
odoo/addons/sale_order_type_quotation_number/views/sale_order_type_view.xml
odoo/addons/sale_order_type_quotation_number/views/sale_views.xml
odoo_addon_sale_order_type_quotation_number-15.0.1.2.0.dist-info/METADATA
odoo_addon_sale_order_type_quotation_number-15.0.1.2.0.dist-info/WHEEL
odoo_addon_sale_order_type_quotation_number-15.0.1.2.0.dist-info/top_level.txt
odoo_addon_sale_order_type_quotation_number-15.0.1.2.0.dist-info/RECORD
