Metadata-Version: 2.1
Name: odoo-addon-sale_order_type_quotation_number
Version: 15.0.1.2.0
Summary: Use quotation sequence depending on sale type
Home-page: https://github.com/OCA/sale-workflow
Author: Sygel, Odoo Community Association (OCA)
Author-email: support@odoo-community.org
License: AGPL-3
Classifier: Programming Language :: Python
Classifier: Framework :: Odoo
Classifier: Framework :: Odoo :: 15.0
Classifier: License :: OSI Approved :: GNU Affero General Public License v3
Requires-Python: >=3.8
Requires-Dist: odoo-addon-sale-order-type <15.1dev,>=15.0dev
Requires-Dist: odoo-addon-sale-quotation-number <15.1dev,>=15.0dev
Requires-Dist: odoo <15.1dev,>=15.0a
